tkvideo/__init__.py
tkvideo/tkvideo.py
tkvideo_moviepy-0.1.0.dist-info/LICENSE
tkvideo_moviepy-0.1.0.dist-info/METADATA
tkvideo_moviepy-0.1.0.dist-info/WHEEL
tkvideo_moviepy-0.1.0.dist-info/top_level.txt
tkvideo_moviepy-0.1.0.dist-info/RECORD
