Metadata-Version: 2.1
Name: tkvideo-moviepy
Version: 0.1.0
Summary: Play moviepy video clips with tkiner
Home-page: https://github.com/MysteryBlokHed/tkvideo-moviepy
Author: Adam Thompson-Sharpe
Author-email: adamthompsonsharpe@gmail.com
License: MIT
Keywords: tkvideo tkinter video display label pillow imageio huskee moviepy
Platform: UNKNOWN
Classifier: License :: OSI Approved :: MIT License
Classifier: Programming Language :: Python :: 3
Classifier: Programming Language :: Python :: 3.6
Classifier: Programming Language :: Python :: 3.7
Classifier: Programming Language :: Python :: 3.8
Classifier: Programming Language :: Python :: 3.9
Classifier: Programming Language :: Python :: 3.10
Classifier: Topic :: Multimedia :: Video :: Display
License-File: LICENSE
Requires-Dist: moviepy
Requires-Dist: Pillow
